portainerlang/__init__.py
portainerlang/main.py
portainerlang/cli/__init__.py
portainerlang/cli/commands.py
portainerlang/logging/__init__.py
portainerlang/logging/logging.py
portainerlang/query/__init__.py
portainerlang/query/query.py
portainerlang/utils/__init__.py
portainerlang/utils/assets.py
portainerlang/utils/download.py
portainerlang/utils/env.py
portainerlang-0.4.0.dist-info/METADATA
portainerlang-0.4.0.dist-info/WHEEL
portainerlang-0.4.0.dist-info/entry_points.txt
portainerlang-0.4.0.dist-info/top_level.txt
portainerlang-0.4.0.dist-info/RECORD
