Metadata-Version: 2.1
Name: portainerlang
Version: 0.4.0
Requires-Dist: bullet (==2.2.0)
Requires-Dist: faiss-cpu (==1.7.4)
Requires-Dist: typing-inspect (==0.9.0)
Requires-Dist: wcwidth (==0.2.13)
Requires-Dist: greenlet (==3.0.3) ; platform_machine == "aarch64" or (platform_machine == "ppc64le" or (platform_machine == "x86_64" or (platform_machine == "amd64" or (platform_machine == "AMD64" or (platform_machine == "win32" or platform_machine == "WIN32")))))
Requires-Dist: charset-normalizer (==3.3.2) ; python_full_version >= "3.7.0"
Requires-Dist: prompt-toolkit (==3.0.43) ; python_full_version >= "3.7.0"
Requires-Dist: rich (==13.7.0) ; python_full_version >= "3.7.0"
Requires-Dist: openai (==1.8.0) ; python_full_version >= "3.7.1"
Requires-Dist: async-timeout (==4.0.3) ; python_version < "3.11"
Requires-Dist: exceptiongroup (==1.2.0) ; python_version < "3.11"
Requires-Dist: langchain (==0.1.1) ; python_version < "4.0" and python_full_version >= "3.8.1"
Requires-Dist: langchain-community (==0.0.13) ; python_version < "4.0" and python_full_version >= "3.8.1"
Requires-Dist: langchain-core (==0.1.12) ; python_version < "4.0" and python_full_version >= "3.8.1"
Requires-Dist: langchain-openai (==0.0.2.post1) ; python_version < "4.0" and python_full_version >= "3.8.1"
Requires-Dist: langsmith (==0.0.82) ; python_version < "4.0" and python_full_version >= "3.8.1"
Requires-Dist: jsonpatch (==1.33) ; python_version >= "2.7" and python_version not in "3.0, 3.1, 3.2, 3.3, 3.4, 3.5, 3.6"
Requires-Dist: jsonpointer (==2.4) ; python_version >= "2.7" and python_version not in "3.0, 3.1, 3.2, 3.3, 3.4, 3.5, 3.6"
Requires-Dist: idna (==3.6) ; python_version >= "3.5"
Requires-Dist: mypy-extensions (==1.0.0) ; python_version >= "3.5"
Requires-Dist: certifi (==2023.11.17) ; python_version >= "3.6"
Requires-Dist: distro (==1.9.0) ; python_version >= "3.6"
Requires-Dist: pyyaml (==6.0.1) ; python_version >= "3.6"
Requires-Dist: aiosignal (==1.3.1) ; python_version >= "3.7"
Requires-Dist: attrs (==23.2.0) ; python_version >= "3.7"
Requires-Dist: h11 (==0.14.0) ; python_version >= "3.7"
Requires-Dist: mdurl (==0.1.2) ; python_version >= "3.7"
Requires-Dist: multidict (==6.0.4) ; python_version >= "3.7"
Requires-Dist: packaging (==23.2) ; python_version >= "3.7"
Requires-Dist: pydantic (==2.5.3) ; python_version >= "3.7"
Requires-Dist: pydantic-core (==2.14.6) ; python_version >= "3.7"
Requires-Dist: pygments (==2.17.2) ; python_version >= "3.7"
Requires-Dist: regex (==2023.12.25) ; python_version >= "3.7"
Requires-Dist: requests (==2.31.0) ; python_version >= "3.7"
Requires-Dist: sniffio (==1.3.0) ; python_version >= "3.7"
Requires-Dist: sqlalchemy (==2.0.25) ; python_version >= "3.7"
Requires-Dist: tenacity (==8.2.3) ; python_version >= "3.7"
Requires-Dist: tqdm (==4.66.1) ; python_version >= "3.7"
Requires-Dist: yarl (==1.9.4) ; python_version >= "3.7"
Requires-Dist: dataclasses-json (==0.6.3) ; python_version >= "3.7" and python_version < "4.0"
Requires-Dist: aiohttp (==3.9.1) ; python_version >= "3.8"
Requires-Dist: annotated-types (==0.6.0) ; python_version >= "3.8"
Requires-Dist: anyio (==4.2.0) ; python_version >= "3.8"
Requires-Dist: frozenlist (==1.4.1) ; python_version >= "3.8"
Requires-Dist: httpcore (==1.0.2) ; python_version >= "3.8"
Requires-Dist: httpx (==0.26.0) ; python_version >= "3.8"
Requires-Dist: markdown-it-py (==3.0.0) ; python_version >= "3.8"
Requires-Dist: marshmallow (==3.20.2) ; python_version >= "3.8"
Requires-Dist: python-dotenv (==1.0.0) ; python_version >= "3.8"
Requires-Dist: tiktoken (==0.5.2) ; python_version >= "3.8"
Requires-Dist: typing-extensions (==4.9.0) ; python_version >= "3.8"
Requires-Dist: urllib3 (==2.1.0) ; python_version >= "3.8"
Requires-Dist: numpy (==1.26.3) ; python_version >= "3.9"
